[{"Year":2017,"Units":"Percent by gender","Value":8.5},{"Year":2017,"Units":"Percent by age","Value":8.5},{"Year":2016,"Units":"Percent by gender","Value":9.0},{"Year":2016,"Units":"Percent by age","Value":9.0},{"Year":2015,"Units":"Percent by gender","Value":9.4},{"Year":2015,"Units":"Percent by age","Value":9.4},{"Year":2014,"Units":"Percent by gender","Value":9.5},{"Year":2014,"Units":"Percent by age","Value":9.5},{"Year":2013,"Units":"Percent by gender","Value":9.5},{"Year":2013,"Units":"Percent by age","Value":9.5},{"Year":2012,"Units":"Percent by gender","Value":8.9},{"Year":2012,"Units":"Percent by age","Value":8.9}]