{"Year":[2010,2011,2012,2013,2014,2015,2016,2010,2010,2011,2011,2012,2012,2013,2013,2014,2014,2015,2015,2016,2016,2010,2010,2010,2010,2010,2010,2011,2011,2011,2011,2011,2011,2012,2012,2012,2012,2012,2012,2013,2013,2013,2013,2013,2013,2014,2014,2014,2014,2014,2014,2015,2015,2015,2015,2015,2015,2016,2016,2016,2016,2016,2016,2010,2010,2010,2011,2011,2011,2012,2012,2012,2013,2013,2013,2014,2014,2014,2015,2015,2015,2016,2016,2016,2010,2010,2010,2011,2011,2011,2012,2012,2012,2013,2013,2013,2014,2014,2014,2015,2015,2015,2016,2016,2016],"Grade":[null,null,null,null,null,null,null,"A","B","A","B","A","B","A","B","A","B","A","B","A","B","A","A","A","B","B","B","A","A","A","B","B","B","A","A","A","B","B","B","A","A","A","B","B","B","A","A","A","B","B","B","A","A","A","B","B","B","A","A","A","B","B","B",null,null,null,null,null,null,null,null,null,null,null,null,null,null,null,null,null,null,null,null,null,null,null,null,null,null,null,null,null,null,null,null,null,null,null,null,null,null,null,null,null,null],"Planet":[null,null,null,null,null,null,null,null,null,null,null,null,null,null,null,null,null,null,null,null,null,"Mercury","Venus","Earth","Mercury","Venus","Earth","Mercury","Venus","Earth","Mercury","Venus","Earth","Mercury","Venus","Earth","Mercury","Venus","Earth","Mercury","Venus","Earth","Mercury","Venus","Earth","Mercury","Venus","Earth","Mercury","Venus","Earth","Mercury","Venus","Earth","Mercury","Venus","Earth","Mercury","Venus","Earth","Mercury","Venus","Earth","Mercury","Venus","Earth","Mercury","Venus","Earth","Mercury","Venus","Earth","Mercury","Venus","Earth","Mercury","Venus","Earth","Mercury","Venus","Earth","Mercury","Venus","Earth",null,null,null,null,null,null,null,null,null,null,null,null,null,null,null,null,null,null,null,null,null],"Fruit":[null,null,null,null,null,null,null,null,null,null,null,null,null,null,null,null,null,null,null,null,null,null,null,null,null,null,null,null,null,null,null,null,null,null,null,null,null,null,null,null,null,null,null,null,null,null,null,null,null,null,null,null,null,null,null,null,null,null,null,null,null,null,null,null,null,null,null,null,null,null,null,null,null,null,null,null,null,null,null,null,null,null,null,null,"Apples","Oranges","Lemons","Apples","Oranges","Lemons","Apples","Oranges","Lemons","Apples","Oranges","Lemons","Apples","Oranges","Lemons","Apples","Oranges","Lemons","Apples","Oranges","Lemons"],"Value":[15.1591,16.3583,16.2244,14.3392,15.79,14.0988,15.5934,14.1695,16.1488,15.5065,17.2102,16.6152,15.8335,14.3857,14.2927,14.6857,16.8942,14.8525,13.3451,16.5992,14.5875,17.3458,13.3825,11.7802,16.4394,16.5942,15.4127,15.669,16.9856,13.8649,13.2586,19.4585,18.9134,16.2654,18.3479,15.2324,15.6618,13.9548,17.8839,11.8379,16.8824,14.4367,11.1883,16.0526,15.6371,16.2951,10.9936,16.7684,14.5468,19.9637,16.1722,13.309,16.5238,14.7246,11.8639,14.424,13.7473,16.5154,14.8001,18.4822,12.4133,15.1595,16.1897,16.8926,14.9884,13.5965,14.4638,18.222,16.3891,15.9636,16.1514,16.5582,11.5131,16.4675,15.0369,15.4209,15.4786,16.4703,12.5865,15.4739,14.236,14.4644,14.9798,17.336,14.8497,14.6733,15.9544,13.4712,18.2388,17.365,16.4877,16.0224,16.163,14.3664,13.5446,15.1066,14.7726,14.6493,17.948,13.0809,13.7446,15.4709,13.7839,15.0604,17.9358]}