{"Year":[2007,2007,2007,2007,2007,2007,2007,2007,2007,2007,2007,2007,2007,2007,2007,2007,2007,2007,2007,2007,2007,2007,2007,2007,2007,2012,2012,2012,2012,2012,2012,2012,2012,2012,2012,2012,2012,2012,2012,2012,2012,2012,2012,2012,2012,2012,2012,2012,2012,2012],"Type of Business":["All Privately-Held","Private Female-owned","Private Male-owned","Private Equally Female-Male Owned","Publicly-Held","All Privately-Held","Private Female-owned","Private Male-owned","Private Equally Female-Male Owned","Publicly-Held","All Privately-Held","Private Female-owned","Private Male-owned","Private Equally Female-Male Owned","Publicly-Held","All Privately-Held","Private Female-owned","Private Male-owned","Private Equally Female-Male Owned","Publicly-Held","All Privately-Held","Private Female-owned","Private Male-owned","Private Equally Female-Male Owned","Publicly-Held","All Privately-Held","Private Female-owned","Private Male-owned","Private Equally Female-Male Owned","Publicly-Held","All Privately-Held","Private Female-owned","Private Male-owned","Private Equally Female-Male Owned","Publicly-Held","All Privately-Held","Private Female-owned","Private Male-owned","Private Equally Female-Male Owned","Publicly-Held","All Privately-Held","Private Female-owned","Private Male-owned","Private Equally Female-Male Owned","Publicly-Held","All Privately-Held","Private Female-owned","Private Male-owned","Private Equally Female-Male Owned","Publicly-Held"],"Number of Businesses":[null,null,null,null,null,null,null,null,null,null,null,null,null,null,null,null,null,null,null,null,null,null,null,null,null,null,null,null,null,null,null,null,null,null,null,null,null,null,null,null,null,null,null,null,null,null,null,null,null,null],"Number of Businesses with Paid Employees":[null,null,null,null,null,"Businesses with Paid Employees","Businesses with Paid Employees","Businesses with Paid Employees","Businesses with Paid Employees","Businesses with Paid Employees",null,null,null,null,null,null,null,null,null,null,null,null,null,null,null,null,null,null,null,null,"Businesses with Paid Employees","Businesses with Paid Employees","Businesses with Paid Employees","Businesses with Paid Employees","Businesses with Paid Employees",null,null,null,null,null,null,null,null,null,null,null,null,null,null,null],"Number of Paid Employees":[null,null,null,null,null,null,null,null,null,null,"Number of Paid Employees","Number of Paid Employees","Number of Paid Employees","Number of Paid Employees","Number of Paid Employees",null,null,null,null,null,null,null,null,null,null,null,null,null,null,null,null,null,null,null,null,"Number of Paid Employees","Number of Paid Employees","Number of Paid Employees","Number of Paid Employees","Number of Paid Employees",null,null,null,null,null,null,null,null,null,null],"Units":["Number","Number","Number","Number","Number","Number","Number","Number","Number","Number","Number","Number","Number","Number","Number","Revenue ($M)","Revenue ($M)","Revenue ($M)","Revenue ($M)","Revenue ($M)","Payroll ($M)","Payroll ($M)","Payroll ($M)","Payroll ($M)","Payroll ($M)","Number","Number","Number","Number","Number","Number","Number","Number","Number","Number","Number","Number","Number","Number","Number","Revenue ($M)","Revenue ($M)","Revenue ($M)","Revenue ($M)","Revenue ($M)","Payroll ($M)","Payroll ($M)","Payroll ($M)","Payroll ($M)","Payroll ($M)"],"Value":[435314,136579,234486,64249,14735,81587,15674,51137,14775,10321,766764,99164,534522,133079,682107,138503,17247,100985,20271,222400,29910,3688,22025,4196,38340,488671,192358,262460,33853,9328,83408,18262,52989,12157,5801,710143,125389,489344,95411,663176,153934,21803,114815,17316,272307,31013,5004,22428,3580,43863]}